django_invitelink/.gitignore
django_invitelink/__init__.py
django_invitelink/admin.py
django_invitelink/models.py
django_invitelink/signals.py
django_invitelink/urls.py
django_invitelink/views.py
django_invitelink/migrations/0001_initial.py
django_invitelink/migrations/__init__.py
django_invitelink/templates/django_invitelink/base.html
django_invitelink/templates/django_invitelink/invite.html
django_invitelink-0.4.0.dist-info/METADATA
django_invitelink-0.4.0.dist-info/WHEEL
django_invitelink-0.4.0.dist-info/licenses/LICENSE
django_invitelink-0.4.0.dist-info/RECORD
