Metadata-Version: 2.4
Name: django-invitelink
Version: 0.4.0
Summary: Invite Links for Django Projects
Project-URL: source, https://github.com/acdh-oeaw/django-invitelink
Project-URL: changelog, https://github.com/acdh-oeaw/django-invitelink/blob/main/CHANGELOG.md
Project-URL: issues, https://github.com/acdh-oeaw/django-invitelink/issues
Author-email: Birger Schacht <birger.schacht@oeaw.ac.at>
License-Expression: MIT
License-File: LICENSE
Requires-Python: >=3.11
Requires-Dist: django>=5.2
